Proyecto2/src/design/display_7.sv
module display_7 (
    input wire clk,
    input wire [1:0] sel,
    input wire [3:0] dig_in,

    output reg [7:0] seg_7,
    output reg [3:0] AN   // ánodos activos en bajo
);

    // -------- BCD → 7 segmentos --------
    // Función combinacional para convertir un dígito BCD a su representación en 7 segmentos
    function [7:0] bcd_to_7seg;
        input [3:0] bcd;
        begin
            case (bcd)
                4'd0: bcd_to_7seg = 8'b00111111;
                4'd1: bcd_to_7seg = 8'b00000110;
                4'd2: bcd_to_7seg = 8'b01011011;
                4'd3: bcd_to_7seg = 8'b01001111;
                4'd4: bcd_to_7seg = 8'b01100110;
                4'd5: bcd_to_7seg = 8'b01101101;
                4'd6: bcd_to_7seg = 8'b01111101;
                4'd7: bcd_to_7seg = 8'b00000111;
                4'd8: bcd_to_7seg = 8'b01111111;
                4'd9: bcd_to_7seg = 8'b01101111;
                default: bcd_to_7seg = 8'b00000000;
            endcase
        end
    endfunction

    // -------- registro de salida --------
    always @(posedge clk) begin
        seg_7 <= bcd_to_7seg(dig_in);
    end

    // -------- activación de dígitos --------
    // Solo un dígito activo a la vez (multiplexado)
    always @(*) begin
        case (sel)
            2'b00: AN = 4'b0001;
            2'b01: AN = 4'b0010;
            2'b10: AN = 4'b0100;
            2'b11: AN = 4'b1000;
        endcase
    end

endmodule

Proyecto2/src/sim/tb_subsistema3.sv
`timescale 1ns/1ps

module tb_subsistema3;

    // ================================
    // SEÑALES
    // ================================
    logic clk;
    logic [1:0] sel;
    logic [3:0] dig_in;

    wire [7:0] seg_7;
    wire [3:0] AN;

    // ================================
    // DUT
    // ================================
    display_7 DUT (
        .clk(clk),
        .sel(sel),
        .dig_in(dig_in),
        .seg_7(seg_7),
        .AN(AN)
    );

    // ================================
    // RELOJ
    // ================================
    initial clk = 0;
    always #10 clk = ~clk; // 50 MHz sim

    // ================================
    // ESTÍMULOS
    // ================================
    initial begin
        // Inicial
        sel = 0;
        dig_in = 0;

        // Esperar
        #50;

        // ============================
        // Probar dígitos 0–9
        // ============================
        repeat (10) begin
            dig_in = dig_in + 1;
            #100;
        end

        // ============================
        // Probar multiplexado
        // ============================
        dig_in = 4'd5;

        sel = 2'b00; #100;
        sel = 2'b01; #100;
        sel = 2'b10; #100;
        sel = 2'b11; #100;

        // ============================
        // Probar valores inválidos
        // ============================
        dig_in = 4'd12; #100;
        dig_in = 4'd15; #100;

        // ============================
        // Fin
        // ============================
        #200;
        $finish;
    end

    // ================================
    // MONITOR
    // ================================
    initial begin
        $display("Tiempo | sel | dig_in | seg_7 | AN");
        $monitor("%0t | %b | %d | %b | %b",
            $time,
            sel,
            dig_in,
            seg_7,
            AN
        );
    end


    initial begin
    $dumpfile("tb_subsistema3.vcd");   // nombre del archivo
    $dumpvars(0, tb_subsistema3);      // guarda TODAS las señales
end

endmodule

Proyecto2/src/build/tb_subsistema3.vcd
$date
	Wed May 06 21:36:55 2026
$end
$version
	Icarus Verilog
$end
$timescale
	1ps
$end
$scope module tb_subsistema3 $end
$var wire 8 ! seg_7 [7:0] $end
$var wire 4 " AN [3:0] $end
$var reg 1 # clk $end
$var reg 4 $ dig_in [3:0] $end
$var reg 2 % sel [1:0] $end
$scope module DUT $end
$var wire 1 # clk $end
$var wire 4 & dig_in [3:0] $end
$var wire 2 ' sel [1:0] $end
$var reg 4 ( AN [3:0] $end
$var reg 8 ) seg_7 [7:0] $end
$scope function bcd_to_7seg $end
$var reg 4 * bcd [3:0] $end
$upscope $end
$upscope $end
$upscope $end
$enddefinitions $end
$comment Show the parameter values. $end
$dumpall
$end
#0
$dumpvars
bx *
bx )
b1 (
b0 '
b0 &
b0 %
b0 $
0#
b1 "
bx !
$end
#10000
b111111 !
b111111 )
b0 *
1#
#20000
0#
#30000
1#
#40000
0#
#50000
b110 !
b110 )
b1 *
1#
b1 $
b1 &
#60000
0#
#70000
1#
#80000
0#
#90000
1#
#100000
0#
#110000
1#
#120000
0#
#130000
1#
#140000
0#
#150000
b1011011 !
b1011011 )
b10 *
1#
b10 $
b10 &
#160000
0#
#170000
1#
#180000
0#
#190000
1#
#200000
0#
#210000
1#
#220000
0#
#230000
1#
#240000
0#
#250000
b1001111 !
b1001111 )
b11 *
1#
b11 $
b11 &
#260000
0#
#270000
1#
#280000
0#
#290000
1#
#300000
0#
#310000
1#
#320000
0#
#330000
1#
#340000
0#
#350000
b1100110 !
b1100110 )
b100 *
1#
b100 $
b100 &
#360000
0#
#370000
1#
#380000
0#
#390000
1#
#400000
0#
#410000
1#
#420000
0#
#430000
1#
#440000
0#
#450000
b1101101 !
b1101101 )
b101 *
1#
b101 $
b101 &
#460000
0#
#470000
1#
#480000
0#
#490000
1#
#500000
0#
#510000
1#
#520000
0#
#530000
1#
#540000
0#
#550000
b1111101 !
b1111101 )
b110 *
1#
b110 $
b110 &
#560000
0#
#570000
1#
#580000
0#
#590000
1#
#600000
0#
#610000
1#
#620000
0#
#630000
1#
#640000
0#
#650000
b111 !
b111 )
b111 *
1#
b111 $
b111 &
#660000
0#
#670000
1#
#680000
0#
#690000
1#
#700000
0#
#710000
1#
#720000
0#
#730000
1#
#740000
0#
#750000
b1111111 !
b1111111 )
b1000 *
1#
b1000 $
b1000 &
#760000
0#
#770000
1#
#780000
0#
#790000
1#
#800000
0#
#810000
1#
#820000
0#
#830000
1#
#840000
0#
#850000
b1101111 !
b1101111 )
b1001 *
1#
b1001 $
b1001 &
#860000
0#
#870000
1#
#880000
0#
#890000
1#
#900000
0#
#910000
1#
#920000
0#
#930000
1#
#940000
0#
#950000
b0 !
b0 )
b1010 *
1#
b1010 $
b1010 &
#960000
0#
#970000
1#
#980000
0#
#990000
1#
#1000000
0#
#1010000
1#
#1020000
0#
#1030000
1#
#1040000
0#
#1050000
b1101101 !
b1101101 )
b101 *
1#
b101 $
b101 &
#1060000
0#
#1070000
1#
#1080000
0#
#1090000
1#
#1100000
0#
#1110000
1#
#1120000
0#
#1130000
1#
#1140000
0#
#1150000
b10 "
b10 (
1#
b1 %
b1 '
#1160000
0#
#1170000
1#
#1180000
0#
#1190000
1#
#1200000
0#
#1210000
1#
#1220000
0#
#1230000
1#
#1240000
0#
#1250000
b100 "
b100 (
1#
b10 %
b10 '
#1260000
0#
#1270000
1#
#1280000
0#
#1290000
1#
#1300000
0#
#1310000
1#
#1320000
0#
#1330000
1#
#1340000
0#
#1350000
b1000 "
b1000 (
1#
b11 %
b11 '
#1360000
0#
#1370000
1#
#1380000
0#
#1390000
1#
#1400000
0#
#1410000
1#
#1420000
0#
#1430000
1#
#1440000
0#
#1450000
b0 !
b0 )
b1100 *
1#
b1100 $
b1100 &
#1460000
0#
#1470000
1#
#1480000
0#
#1490000
1#
#1500000
0#
#1510000
1#
#1520000
0#
#1530000
1#
#1540000
0#
#1550000
b1111 *
1#
b1111 $
b1111 &
