src/design/LEDS_display.sv
module LEDS_display (
    input  logic [3:0] data_corregida, //Datos de 4 bits para mostrar en los LEDs,
    output logic [3:0] leds
);

    assign leds = data_corregida;

endmodule

src/design/recep_7_seg.sv
module recep_7_seg (
    input wire [3:0] datos,  // datos D2, D2, D1 Y D0
    output wire [6:0] seg_7 ///a, b, c, d, e, f, g
    );

    wire d3 = datos[3], 
    d2 = datos[2],
    d1 = datos[1],
    d0 = datos[0];

    assign seg_7[0] = (!d2 & !d0) | 
                    (d3 & !d0) | 
                    (d2 & d1) | 
                    (!d3 & d1) | 
                    (d3 & !d2 & !d1) | 
                    (!d3 & d2 & d0); //este es segmento A

    assign seg_7[1] = (!d2 & !d0) | 
                        (!d3 & !d2) | 
                        (!d3 & !d1 & !d0) | 
                        (d3 & !d1 & d0) | 
                        (!d3 & d1 & d0); // este es segmento B

    assign seg_7[2] = (!d3 & d2) | 
                        (d3 & !d2) | 
                        (!d1 & d0) | 
                        (d3 & d1) | 
                        (!d3 & d0); // este es segmento C   

    assign seg_7[3] = (!d3 & !d1)       | (!d2 & d1 & !d0) | (!d2 & d1 & d0) |
                  (d2 & !d1 & d0)   | (!d3 & d1 & !d0) | (d2 & d1 & !d0) |
                  (!d3 & !d2 & !d0); // término que faltaba

    assign seg_7[4] = (!d2 & !d0) | 
                        (d3 & d2) |     
                        (d3 & d1) | 
                        (d1 & !d0); // E

    assign seg_7[5] = (!d1 & !d0) | 
                        (d3 & !d2) | 
                        (d3 & d1) | 
                        (d2 & !d0) | 
                        (!d3 & d2 & !d1); // F

    assign seg_7[6] = (d3 & !d2) | 
                        (d1 & !d0) | 
                        (d3 & d0) | 
                        (!d3 & d2 & !d1) | 
                        (!d3 & !d2 & d1); // G

    
endmodule

src/design_receptor/corrector_error.v
module corrector_error (
    input wire [6:0] recibido,  //código de Hamming recibido del transmisor del otro grupo
    input wire [2:0] sindrome, //Nos permite detectar la posición del error en el código
    output wire [3:0] dato_corregido ); // Código corregido


    //definimos s2, s1, y s0 desde el bus
    wire s2 = sindrome[2];
    wire s1 = sindrome[1];
    wire s0 = sindrome[0];


    //Lógica del decoder de 3 a 8 (por 2^3)
    wire y1 = !s2 & !s1 & s0;    //Posición 1
    wire y2 = !s2 & s1 & !s0;    // Posición 2
    wire y3 = !s2 & s1 & s0;    // Posición 3 (D0)
    wire y4 = s2 & !s1 & !s0;   // Posición 4
    wire y5 = s2 & !s1 & s0;   // Posición 5 (D1)
    wire y6 = s2 & s1 & !s0;    // Posición 6 (D2)
    wire y7 = s2 & s1 & s0;     // Posición 7 (D3)


    //Ahora hacemos los XORs para para eliminar el error en el código
    wire [6:0] limpio;
    assign limpio[0] = recibido[0] ^ y1;
    assign limpio[1] = recibido[1] ^ y2;
    assign limpio[2] = recibido[2] ^ y3;
    assign limpio[3] = recibido[3] ^ y4;
    assign limpio[4] = recibido[4] ^ y5;
    assign limpio[5] = recibido[5] ^ y6;
    assign limpio[6] = recibido[6] ^ y7;

    //Por último extraemos datos finales
    assign dato_corregido = {limpio[6], limpio[5], limpio[4], limpio[2]};


endmodule







    
endmodule

src/design/decoder_paridad.sv
module decoder_paridad (
    input wire [6:0] recibido,     // R7 a R1
    output wire [2:0] pos_error    // s2, s1, s0
);

    // -----------------------------
    // Mapeo del mensaje recibido
    // -----------------------------
    wire r1, r2, r3, r4, r5, r6, r7;

    assign r1 = recibido[0];
    assign r2 = recibido[1];
    assign r3 = recibido[2];
    assign r4 = recibido[3];
    assign r5 = recibido[4];
    assign r6 = recibido[5];
    assign r7 = recibido[6];

    // -----------------------------
    // Cálculo del síndrome
    // -----------------------------
    wire s0, s1, s2;

    assign s0 = r1 ^ r3 ^ r5 ^ r7;
    assign s1 = r2 ^ r3 ^ r6 ^ r7;
    assign s2 = r4 ^ r5 ^ r6 ^ r7;

    // -----------------------------
    // Salida
    // -----------------------------
    assign pos_error = {s2, s1, s0};

endmodule

src/design/top_recep.sv
module top_recep (
    input  wire [6:0] data_in,
    output wire [3:0] data_out,      // dato corregido → va a LEDs y a selector
    output wire [2:0] pos_error,     // síndrome → va a selector
    output wire [6:0] seg_7,
    output wire [3:0] leds_out
);
    wire [2:0] sindrome;

    decoder_paridad decodificador_paridad (
        .recibido(data_in),
        .pos_error(sindrome)
    );

    corrector_error corrector (
        .recibido(data_in),
        .sindrome(sindrome),
        .dato_corregido(data_out)
    );

    recep_7_seg decodificador (
        .datos(data_out),
        .seg_7(seg_7)
    );

    LEDS_display leds (
        .data_corregida(data_out),
        .leds(leds_out)
    );

    assign pos_error = sindrome;  // expone el síndrome hacia el selector externo

endmodule

src/sim/top_recep_tb.sv
`timescale 1ns/1ps

module top_recep_tb;

    reg  [6:0] data_in;
    wire [3:0] data_out;
    wire [6:0] seg_7;
    wire [3:0] leds_out;

    top_recep uut (
        .data_in(data_in),
        .data_out(data_out),
        .seg_7(seg_7),
        .leds_out(leds_out)
    );

    initial begin
        $dumpfile("top_recep_tb.vcd");
        $dumpvars(0, top_recep_tb);

        $display("Inicio de simulación...");
        $display("==========================================================");

        // Para cada caso: primero probamos sin error, luego con error en cada bit
        // Los codewords vienen directamente de las salidas verificadas del transmisor

        // data_in=0000 -> codeword=0000000 -> dato esperado=0000
        data_in = 7'b0000000; #10;
        $display("dato=0000 | sin error     | data_in=%b -> data_out=%b %s", data_in, data_out, (data_out==4'b0000) ? "OK" : "ERROR");
        data_in = 7'b0000001; #10;
        $display("dato=0000 | error bit 0   | data_in=%b -> data_out=%b %s", data_in, data_out, (data_out==4'b0000) ? "OK" : "ERROR");
        data_in = 7'b0000010; #10;
        $display("dato=0000 | error bit 1   | data_in=%b -> data_out=%b %s", data_in, data_out, (data_out==4'b0000) ? "OK" : "ERROR");
        data_in = 7'b0000100; #10;
        $display("dato=0000 | error bit 2   | data_in=%b -> data_out=%b %s", data_in, data_out, (data_out==4'b0000) ? "OK" : "ERROR");
        data_in = 7'b0001000; #10;
        $display("dato=0000 | error bit 3   | data_in=%b -> data_out=%b %s", data_in, data_out, (data_out==4'b0000) ? "OK" : "ERROR");
        data_in = 7'b0010000; #10;
        $display("dato=0000 | error bit 4   | data_in=%b -> data_out=%b %s", data_in, data_out, (data_out==4'b0000) ? "OK" : "ERROR");
        data_in = 7'b0100000; #10;
        $display("dato=0000 | error bit 5   | data_in=%b -> data_out=%b %s", data_in, data_out, (data_out==4'b0000) ? "OK" : "ERROR");
        data_in = 7'b1000000; #10;
        $display("dato=0000 | error bit 6   | data_in=%b -> data_out=%b %s", data_in, data_out, (data_out==4'b0000) ? "OK" : "ERROR");

        $display("----------------------------------------------------------");

        // data_in=0001 -> codeword=0000111 -> dato esperado=0001
        data_in = 7'b0000111; #10;
        $display("dato=0001 | sin error     | data_in=%b -> data_out=%b %s", data_in, data_out, (data_out==4'b0001) ? "OK" : "ERROR");
        data_in = 7'b0000110; #10;
        $display("dato=0001 | error bit 0   | data_in=%b -> data_out=%b %s", data_in, data_out, (data_out==4'b0001) ? "OK" : "ERROR");
        data_in = 7'b0000101; #10;
        $display("dato=0001 | error bit 1   | data_in=%b -> data_out=%b %s", data_in, data_out, (data_out==4'b0001) ? "OK" : "ERROR");
        data_in = 7'b0000011; #10;
        $display("dato=0001 | error bit 2   | data_in=%b -> data_out=%b %s", data_in, data_out, (data_out==4'b0001) ? "OK" : "ERROR");
        data_in = 7'b0001111; #10;
        $display("dato=0001 | error bit 3   | data_in=%b -> data_out=%b %s", data_in, data_out, (data_out==4'b0001) ? "OK" : "ERROR");
        data_in = 7'b0010111; #10;
        $display("dato=0001 | error bit 4   | data_in=%b -> data_out=%b %s", data_in, data_out, (data_out==4'b0001) ? "OK" : "ERROR");
        data_in = 7'b0100111; #10;
        $display("dato=0001 | error bit 5   | data_in=%b -> data_out=%b %s", data_in, data_out, (data_out==4'b0001) ? "OK" : "ERROR");
        data_in = 7'b1000111; #10;
        $display("dato=0001 | error bit 6   | data_in=%b -> data_out=%b %s", data_in, data_out, (data_out==4'b0001) ? "OK" : "ERROR");

        $display("----------------------------------------------------------");

        // data_in=0110 -> codeword=0110011 -> dato esperado=0110
        data_in = 7'b0110011; #10;
        $display("dato=0110 | sin error     | data_in=%b -> data_out=%b %s", data_in, data_out, (data_out==4'b0110) ? "OK" : "ERROR");
        data_in = 7'b0110010; #10;
        $display("dato=0110 | error bit 0   | data_in=%b -> data_out=%b %s", data_in, data_out, (data_out==4'b0110) ? "OK" : "ERROR");
        data_in = 7'b0110001; #10;
        $display("dato=0110 | error bit 1   | data_in=%b -> data_out=%b %s", data_in, data_out, (data_out==4'b0110) ? "OK" : "ERROR");
        data_in = 7'b0110111; #10;
        $display("dato=0110 | error bit 2   | data_in=%b -> data_out=%b %s", data_in, data_out, (data_out==4'b0110) ? "OK" : "ERROR");
        data_in = 7'b0111011; #10;
        $display("dato=0110 | error bit 3   | data_in=%b -> data_out=%b %s", data_in, data_out, (data_out==4'b0110) ? "OK" : "ERROR");
        data_in = 7'b0100011; #10;
        $display("dato=0110 | error bit 4   | data_in=%b -> data_out=%b %s", data_in, data_out, (data_out==4'b0110) ? "OK" : "ERROR");
        data_in = 7'b0010011; #10;
        $display("dato=0110 | error bit 5   | data_in=%b -> data_out=%b %s", data_in, data_out, (data_out==4'b0110) ? "OK" : "ERROR");
        data_in = 7'b1110011; #10;
        $display("dato=0110 | error bit 6   | data_in=%b -> data_out=%b %s", data_in, data_out, (data_out==4'b0110) ? "OK" : "ERROR");

        $display("----------------------------------------------------------");

        // data_in=1001 -> codeword=1001100 -> dato esperado=1001
        data_in = 7'b1001100; #10;
        $display("dato=1001 | sin error     | data_in=%b -> data_out=%b %s", data_in, data_out, (data_out==4'b1001) ? "OK" : "ERROR");
        data_in = 7'b1001101; #10;
        $display("dato=1001 | error bit 0   | data_in=%b -> data_out=%b %s", data_in, data_out, (data_out==4'b1001) ? "OK" : "ERROR");
        data_in = 7'b1001110; #10;
        $display("dato=1001 | error bit 1   | data_in=%b -> data_out=%b %s", data_in, data_out, (data_out==4'b1001) ? "OK" : "ERROR");
        data_in = 7'b1001000; #10;
        $display("dato=1001 | error bit 2   | data_in=%b -> data_out=%b %s", data_in, data_out, (data_out==4'b1001) ? "OK" : "ERROR");
        data_in = 7'b1000100; #10;
        $display("dato=1001 | error bit 3   | data_in=%b -> data_out=%b %s", data_in, data_out, (data_out==4'b1001) ? "OK" : "ERROR");
        data_in = 7'b1011100; #10;
        $display("dato=1001 | error bit 4   | data_in=%b -> data_out=%b %s", data_in, data_out, (data_out==4'b1001) ? "OK" : "ERROR");
        data_in = 7'b1101100; #10;
        $display("dato=1001 | error bit 5   | data_in=%b -> data_out=%b %s", data_in, data_out, (data_out==4'b1001) ? "OK" : "ERROR");
        data_in = 7'b0001100; #10;
        $display("dato=1001 | error bit 6   | data_in=%b -> data_out=%b %s", data_in, data_out, (data_out==4'b1001) ? "OK" : "ERROR");

        $display("==========================================================");
        $display("Fin de simulación");
        $finish;
    end

endmodule

src/build/top_recep_tb.vcd
$date
	Thu Apr 16 01:10:37 2026
$end
$version
	Icarus Verilog
$end
$timescale
	1ps
$end
$scope module top_recep_tb $end
$var wire 7 ! seg_7 [6:0] $end
$var wire 4 " leds_out [3:0] $end
$var wire 4 # data_out [3:0] $end
$var reg 7 $ data_in [6:0] $end
$scope module uut $end
$var wire 7 % data_in [6:0] $end
$var wire 3 & pos_error [2:0] $end
$var wire 3 ' sindrome [2:0] $end
$var wire 7 ( seg_7 [6:0] $end
$var wire 4 ) leds_out [3:0] $end
$var wire 4 * data_out [3:0] $end
$scope module corrector $end
$var wire 7 + recibido [6:0] $end
$var wire 1 , y1 $end
$var wire 1 - y2 $end
$var wire 1 . y3 $end
$var wire 1 / y4 $end
$var wire 1 0 y5 $end
$var wire 1 1 y6 $end
$var wire 1 2 y7 $end
$var wire 3 3 sindrome [2:0] $end
$var wire 1 4 s2 $end
$var wire 1 5 s1 $end
$var wire 1 6 s0 $end
$var wire 7 7 limpio [6:0] $end
$var wire 4 8 dato_corregido [3:0] $end
$upscope $end
$scope module decodificador $end
$var wire 4 9 datos [3:0] $end
$var wire 7 : seg_7 [6:0] $end
$var wire 1 ; d3 $end
$var wire 1 < d2 $end
$var wire 1 = d1 $end
$var wire 1 > d0 $end
$upscope $end
$scope module decodificador_paridad $end
$var wire 7 ? recibido [6:0] $end
$var wire 1 @ s0 $end
$var wire 1 A s1 $end
$var wire 1 B s2 $end
$var wire 1 C r7 $end
$var wire 1 D r6 $end
$var wire 1 E r5 $end
$var wire 1 F r4 $end
$var wire 1 G r3 $end
$var wire 1 H r2 $end
$var wire 1 I r1 $end
$var wire 3 J pos_error [2:0] $end
$upscope $end
$scope module leds $end
$var wire 4 K data_corregida [3:0] $end
$var wire 4 L leds [3:0] $end
$upscope $end
$upscope $end
$upscope $end
$enddefinitions $end
$comment Show the parameter values. $end
$dumpall
$end
#0
$dumpvars
b0 L
b0 K
b0 J
0I
0H
0G
0F
0E
0D
0C
0B
0A
0@
b0 ?
0>
0=
0<
0;
b111011 :
b0 9
b0 8
b0 7
06
05
04
b0 3
02
01
00
0/
0.
0-
0,
b0 +
b0 *
b0 )
b111011 (
b0 '
b0 &
b0 %
b0 $
b0 #
b0 "
b111011 !
$end
#10000
1,
16
b1 &
b1 '
b1 3
b1 J
1@
b0 7
1I
b1 $
b1 %
b1 +
b1 ?
#20000
1-
0,
15
06
1A
b10 &
b10 '
b10 3
b10 J
0@
b0 7
1H
0I
b10 $
b10 %
b10 +
b10 ?
#30000
b111011 !
b111011 (
b111011 :
0-
1.
16
0>
b11 &
b11 '
b11 3
b11 J
1@
b0 "
b0 )
b0 L
b0 #
b0 *
b0 8
b0 9
b0 K
b0 7
1G
0H
b100 $
b100 %
b100 +
b100 ?
#40000
1/
b111011 !
b111011 (
b111011 :
0-
0.
14
05
06
0>
1B
0A
b100 &
b100 '
b100 3
b100 J
0@
b0 "
b0 )
b0 L
b0 #
b0 *
b0 8
b0 9
b0 K
b0 7
1F
0G
b1000 $
b1000 %
b1000 +
b1000 ?
#50000
b111011 !
b111011 (
b111011 :
0/
10
0=
16
b0 "
b0 )
b0 L
b0 #
b0 *
b0 8
b0 9
b0 K
b101 &
b101 '
b101 3
b101 J
1@
b0 7
1E
0F
b10000 $
b10000 %
b10000 +
b10000 ?
#60000
b111011 !
b111011 (
b111011 :
11
0/
00
0=
0<
15
06
b0 "
b0 )
b0 L
b0 #
b0 *
b0 8
b0 9
b0 K
1A
b110 &
b110 '
b110 3
b110 J
0@
b0 7
1D
0E
b100000 $
b100000 %
b100000 +
b100000 ?
#70000
b111011 !
b111011 (
b111011 :
0<
0;
01
12
b0 "
b0 )
b0 L
b0 #
b0 *
b0 8
b0 9
b0 K
16
b0 7
b111 &
b111 '
b111 3
b111 J
1@
1C
0D
b1000000 $
b1000000 %
b1000000 +
b1000000 ?
#80000
b1110 !
b1110 (
b1110 :
0<
1>
0;
01
02
b1 "
b1 )
b1 L
b1 #
b1 *
b1 8
b1 9
b1 K
04
05
06
b111 7
0B
0A
b0 &
b0 '
b0 3
b0 J
0@
0C
1G
1H
1I
b111 $
b111 %
b111 +
b111 ?
#90000
1,
16
b1 &
b1 '
b1 3
b1 J
1@
b111 7
0I
b110 $
b110 %
b110 +
b110 ?
#100000
1-
0,
15
06
1A
b10 &
b10 '
b10 3
b10 J
0@
b111 7
0H
1I
b101 $
b101 %
b101 +
b101 ?
#110000
b1110 !
b1110 (
b1110 :
0-
1.
16
1>
b11 &
b11 '
b11 3
b11 J
1@
b1 "
b1 )
b1 L
b1 #
b1 *
b1 8
b1 9
b1 K
b111 7
0G
1H
b11 $
b11 %
b11 +
b11 ?
#120000
b1110 !
b1110 (
b1110 :
1/
0-
0.
14
05
06
1>
1B
0A
b100 &
b100 '
b100 3
b100 J
0@
b1 "
b1 )
b1 L
b1 #
b1 *
b1 8
b1 9
b1 K
b111 7
1F
1G
b1111 $
b1111 %
b1111 +
b1111 ?
#130000
b1110 !
b1110 (
b1110 :
0/
10
0=
16
b1 "
b1 )
b1 L
b1 #
b1 *
b1 8
b1 9
b1 K
b101 &
b101 '
b101 3
b101 J
1@
b111 7
1E
0F
b10111 $
b10111 %
b10111 +
b10111 ?
#140000
b1110 !
b1110 (
b1110 :
11
0/
00
0=
0<
15
06
b1 "
b1 )
b1 L
b1 #
b1 *
b1 8
b1 9
b1 K
1A
b110 &
b110 '
b110 3
b110 J
0@
b111 7
1D
0E
b100111 $
b100111 %
b100111 +
b100111 ?
#150000
b1110 !
b1110 (
b1110 :
0<
0;
01
12
b1 "
b1 )
b1 L
b1 #
b1 *
b1 8
b1 9
b1 K
16
b111 7
b111 &
b111 '
b111 3
b111 J
1@
1C
0D
b1000111 $
b1000111 %
b1000111 +
b1000111 ?
#160000
b1111101 !
b1111101 (
b1111101 :
0>
1=
1<
0;
01
02
b110 "
b110 )
b110 L
b110 #
b110 *
b110 8
b110 9
b110 K
04
05
06
b110011 7
0B
0A
b0 &
b0 '
b0 3
b0 J
0@
0C
1D
1E
0G
b110011 $
b110011 %
b110011 +
b110011 ?
#170000
1,
16
b1 &
b1 '
b1 3
b1 J
1@
b110011 7
0I
b110010 $
b110010 %
b110010 +
b110010 ?
#180000
1-
0,
15
06
1A
b10 &
b10 '
b10 3
b10 J
0@
b110011 7
0H
1I
b110001 $
b110001 %
b110001 +
b110001 ?
#190000
b1111101 !
b1111101 (
b1111101 :
0-
1.
16
0>
b11 &
b11 '
b11 3
b11 J
1@
b110 "
b110 )
b110 L
b110 #
b110 *
b110 8
b110 9
b110 K
b110011 7
1G
1H
b110111 $
b110111 %
b110111 +
b110111 ?
#200000
1/
b1111101 !
b1111101 (
b1111101 :
0-
0.
14
05
06
0>
1B
0A
b100 &
b100 '
b100 3
b100 J
0@
b110 "
b110 )
b110 L
b110 #
b110 *
b110 8
b110 9
b110 K
b110011 7
1F
0G
b111011 $
b111011 %
b111011 +
b111011 ?
#210000
b1111101 !
b1111101 (
b1111101 :
0/
10
1=
16
b110 "
b110 )
b110 L
b110 #
b110 *
b110 8
b110 9
b110 K
b101 &
b101 '
b101 3
b101 J
1@
b110011 7
0E
0F
b100011 $
b100011 %
b100011 +
b100011 ?
#220000
b1111101 !
b1111101 (
b1111101 :
11
0/
00
1=
1<
15
06
b110 "
b110 )
b110 L
b110 #
b110 *
b110 8
b110 9
b110 K
1A
b110 &
b110 '
b110 3
b110 J
0@
b110011 7
0D
1E
b10011 $
b10011 %
b10011 +
b10011 ?
#230000
b1111101 !
b1111101 (
b1111101 :
1<
0;
01
12
b110 "
b110 )
b110 L
b110 #
b110 *
b110 8
b110 9
b110 K
16
b110011 7
b111 &
b111 '
b111 3
b111 J
1@
1C
1D
b1110011 $
b1110011 %
b1110011 +
b1110011 ?
#240000
1;
b1100111 !
b1100111 (
b1100111 :
01
02
1>
0=
0<
04
05
06
b1001 "
b1001 )
b1001 L
b1001 #
b1001 *
b1001 8
b1001 9
b1001 K
0B
0A
b0 &
b0 '
b0 3
b0 J
0@
b1001100 7
0D
0E
1F
1G
0H
0I
b1001100 $
b1001100 %
b1001100 +
b1001100 ?
#250000
1,
16
b1 &
b1 '
b1 3
b1 J
1@
b1001100 7
1I
b1001101 $
b1001101 %
b1001101 +
b1001101 ?
#260000
1-
0,
15
06
1A
b10 &
b10 '
b10 3
b10 J
0@
b1001100 7
1H
0I
b1001110 $
b1001110 %
b1001110 +
b1001110 ?
#270000
b1100111 !
b1100111 (
b1100111 :
0-
1.
16
1>
b11 &
b11 '
b11 3
b11 J
1@
b1001 "
b1001 )
b1001 L
b1001 #
b1001 *
b1001 8
b1001 9
b1001 K
b1001100 7
0G
0H
b1001000 $
b1001000 %
b1001000 +
b1001000 ?
#280000
b1100111 !
b1100111 (
b1100111 :
1/
0-
0.
14
05
06
1>
1B
0A
b100 &
b100 '
b100 3
b100 J
0@
b1001 "
b1001 )
b1001 L
b1001 #
b1001 *
b1001 8
b1001 9
b1001 K
b1001100 7
0F
1G
b1000100 $
b1000100 %
b1000100 +
b1000100 ?
#290000
b1100111 !
b1100111 (
b1100111 :
0/
10
0=
16
b1001 "
b1001 )
b1001 L
b1001 #
b1001 *
b1001 8
b1001 9
b1001 K
b101 &
b101 '
b101 3
b101 J
1@
b1001100 7
1E
1F
b1011100 $
b1011100 %
b1011100 +
b1011100 ?
#300000
b1100111 !
b1100111 (
b1100111 :
11
0/
00
0=
0<
15
06
b1001 "
b1001 )
b1001 L
b1001 #
b1001 *
b1001 8
b1001 9
b1001 K
1A
b110 &
b110 '
b110 3
b110 J
0@
b1001100 7
1D
0E
b1101100 $
b1101100 %
b1101100 +
b1101100 ?
#310000
b1100111 !
b1100111 (
b1100111 :
0<
1;
01
12
b1001 "
b1001 )
b1001 L
b1001 #
b1001 *
b1001 8
b1001 9
b1001 K
16
b1001100 7
b111 &
b111 '
b111 3
b111 J
1@
0C
0D
b1100 $
b1100 %
b1100 +
b1100 ?
