src/design_transmisor/hamm_encoder.sv

//Como input se recibe el mensaje de 4 bits y como output genera un código de hamming con 4 bits de información y 3 de paridad
module hamm_encoder (
    input wire [3:0] data_in, output[6:0] data_out);  // porque se trabaja con Hamming (7,4)

    wire d0, d1, d2, d3;  //cables internos para los bits de información

    wire p1, p2, p3;  //cables internos para bits de paridad


    assign p1 = data_in[0] ^ data_in[1] ^ data_in[3] ; //chequea datos en posiciones 3, 5 y 7
    assign p2 = data_in[0] ^ data_in[2] ^ data_in[3] ; //chequea datos en posiciones 3, 6 y 7
    assign p3 = data_in[1] ^ data_in[2] ^ data_in[3]; //chequea datos en posiciones 5, 6 y 7


    //Asignamos el output del código de Hamming. Este va en el orden:
    // d3 | d2 | d1 | p3 | d0 | p2 | p1 |
    assign data_out = {data_in[3], data_in[2], data_in[1], p3, data_in[0], p2, p1};

endmodule

src/design/inyector_error.sv
// Se le "inyecta" un error al código de Hamming para probar la detección de errores del receptor de otro grupo

module inyector_error (
    input wire [6:0] msj_puro, //Código generado en hamm_encoder
    input wire [2:0] sw_error, //switches de posición (S2, S1 o S0)
    output wire [6:0] msj_con_error);


    //Definimos s2, s1 y s0 desde switches
    wire s2 = sw_error[2];
    wire s1 = sw_error[1];
    wire s0 = sw_error[0];


    //Decoder 3 a 8 que activa 1 de las 8 salidas
   // wire y0 = !s2 & !s1 & !s0 no se añade porque no inyecta ningún error
    wire y1 = !s2 & !s1 & s0; 
    wire y2 = !s2 & s1 & !s0;
    wire y3 = !s2 & s1 & s0;
    wire y4 = s2 & !s1 & !s0;
    wire y5 = s2 & !s1 & s0;
    wire y6 = s2 & s1 & !s0;
    wire y7 = s2 & s1 & s0;

    //Ahora, se inyecta el error con un los XOR en la posición respectiva del mensaje recibido
    assign msj_con_error[0] = msj_puro[0] ^ y1;
    assign msj_con_error[1] = msj_puro[1] ^ y2;
    assign msj_con_error[2] = msj_puro[2] ^ y3;
    assign msj_con_error[3] = msj_puro[3] ^ y4;
    assign msj_con_error[4] = msj_puro[4] ^ y5;
    assign msj_con_error[5] = msj_puro[5] ^ y6;
    assign msj_con_error[6] = msj_puro[6] ^ y7;

endmodule

    
/*module top_trans_tb();

    // Señales del test bench
    reg [3:0] data_in;
    wire [6:0] data_out;
    
    // Instancia del módulo a probar
    hamm_encoder uut (
        .data_in(data_in),
        .data_out(data_out)
    );
    
    // Procedimiento de prueba
    initial begin
        $display("==================================================");
        $display("        TEST BENCH - HAMMING (7,4) ENCODER");
        $display("==================================================");
        $display("Data_in (D3 D2 D1 D0) | Data_out (D3 D2 D1 P3 D0 P2 P1)");
        $display("--------------------------------------------------");
        
        // Caso de prueba 1: data_in = 0000
        data_in = 4'b0000;
        #10;
        $display("    %b              |    %b", data_in, data_out);
        
        // Caso de prueba 2: data_in = 0001
        data_in = 4'b0001;
        #10;
        $display("    %b              |    %b", data_in, data_out);
        
        // Caso de prueba 3: data_in = 0010
        data_in = 4'b0010;
        #10;
        $display("    %b              |    %b", data_in, data_out);
        
        // Caso de prueba 4: data_in = 0011
        data_in = 4'b0011;
        #10;
        $display("    %b              |    %b", data_in, data_out);
        
        // Caso de prueba 5: data_in = 0100
        data_in = 4'b0100;
        #10;
        $display("    %b              |    %b", data_in, data_out);
        
        // Caso de prueba 6: data_in = 0101
        data_in = 4'b0101;
        #10;
        $display("    %b              |    %b", data_in, data_out);
        
        // Caso de prueba 7: data_in = 0110
        data_in = 4'b0110;
        #10;
        $display("    %b              |    %b", data_in, data_out);
        
        // Caso de prueba 8: data_in = 0111
        data_in = 4'b0111;
        #10;
        $display("    %b              |    %b", data_in, data_out);
        
        // Caso de prueba 9: data_in = 1000
        data_in = 4'b1000;
        #10;
        $display("    %b              |    %b", data_in, data_out);
        
        // Caso de prueba 10: data_in = 1001
        data_in = 4'b1001;
        #10;
        $display("    %b              |    %b", data_in, data_out);
        
        // Caso de prueba 11: data_in = 1010
        data_in = 4'b1010;
        #10;
        $display("    %b              |    %b", data_in, data_out);
        
        // Caso de prueba 12: data_in = 1011
        data_in = 4'b1011;
        #10;
        $display("    %b              |    %b", data_in, data_out);
        
        // Caso de prueba 13: data_in = 1100
        data_in = 4'b1100;
        #10;
        $display("    %b              |    %b", data_in, data_out);
        
        // Caso de prueba 14: data_in = 1101
        data_in = 4'b1101;
        #10;
        $display("    %b              |    %b", data_in, data_out);
        
        // Caso de prueba 15: data_in = 1110
        data_in = 4'b1110;
        #10;
        $display("    %b              |    %b", data_in, data_out);
        
        // Caso de prueba 16: data_in = 1111
        data_in = 4'b1111;
        #10;
        $display("    %b              |    %b", data_in, data_out);
        
        $display("--------------------------------------------------");
        $display("              SIMULACION COMPLETADA");
        $display("==================================================");
        
        #10;
        $finish;
    end
    
    // Monitor automático para verificar resultados (opcional)
    initial begin
        $monitor("Time = %0t ns: data_in = %b, data_out = %b", $time, data_in, data_out);
    end
    
    // Generación de forma de onda (para quienes usen GTKWave o similar)
    initial begin
        $dumpfile("top_trans_tb.vcd");
        $dumpvars(0, top_trans_tb);
    end

endmodule /*

src/build/top_trans_tb.vcd
$date
	Mon Apr 13 19:52:08 2026
$end
$version
	Icarus Verilog
$end
$timescale
	1ps
$end
$scope module top_trans_tb $end
$var wire 7 ! data_out [6:0] $end
$var reg 4 " data_in [3:0] $end
$scope module uut $end
$var wire 4 # data_in [3:0] $end
$var wire 1 $ p1 $end
$var wire 1 % p2 $end
$var wire 1 & p3 $end
$var wire 7 ' data_out [6:0] $end
$upscope $end
$upscope $end
$enddefinitions $end
$comment Show the parameter values. $end
$dumpall
$end
#0
$dumpvars
b0 '
0&
0%
0$
b0 #
b0 "
b0 !
$end
#10000
1$
1%
b111 !
b111 '
b1 "
b1 #
#20000
0%
1&
b11001 !
b11001 '
b10 "
b10 #
#30000
0$
1%
b11110 !
b11110 '
b11 "
b11 #
#40000
b101010 !
b101010 '
b100 "
b100 #
#50000
1$
0%
b101101 !
b101101 '
b101 "
b101 #
#60000
1%
0&
b110011 !
b110011 '
b110 "
b110 #
#70000
0$
0%
b110100 !
b110100 '
b111 "
b111 #
#80000
1$
1%
1&
b1001011 !
b1001011 '
b1000 "
b1000 #
#90000
0$
0%
b1001100 !
b1001100 '
b1001 "
b1001 #
#100000
1%
0&
b1010010 !
b1010010 '
b1010 "
b1010 #
#110000
1$
0%
b1010101 !
b1010101 '
b1011 "
b1011 #
#120000
b1100001 !
b1100001 '
b1100 "
b1100 #
#130000
0$
1%
b1100110 !
b1100110 '
b1101 "
b1101 #
#140000
0%
1&
b1111000 !
b1111000 '
b1110 "
b1110 #
#150000
1$
1%
b1111111 !
b1111111 '
b1111 "
b1111 #
