src/design/LEDS_display.sv
module LEDS_display (
    input  logic [3:0] data_corregida, //Datos de 4 bits para mostrar en los LEDs,
    output logic [3:0] leds
);

    assign leds = data_corregida;

endmodule

src/design/recep_7_seg.sv
module recep_7_seg (
    input wire [3:0] datos,  // datos D2, D2, D1 Y D0
    output wire [6:0] seg_7 ///a, b, c, d, e, f, g
    );

    wire d3 = datos[3], 
    d2 = datos[2],
    d1 = datos[1],
    d0 = datos[0];

    assign seg_7[0] = (!d2 & !d0) | 
                    (d3 & !d0) | 
                    (d2 & d1) | 
                    (!d3 & d1) | 
                    (d3 & !d2 & !d1) | 
                    (!d3 & d2 & d0); //este es segmento A

    assign seg_7[1] = (!d2 & !d0) | 
                        (!d3 & !d2) | 
                        (!d3 & !d1 & !d0) | 
                        (d3 & !d1 & d0) | 
                        (!d3 & d1 & d0); // este es segmento B

    assign seg_7[2] = (!d3 & d2) | 
                        (d3 & !d2) | 
                        (!d1 & d0) | 
                        (d3 & d1) | 
                        (!d3 & d0); // este es segmento C   

    assign seg_7[3] = (!d3 & !d1)       | (!d2 & d1 & !d0) | (!d2 & d1 & d0) |
                  (d2 & !d1 & d0)   | (!d3 & d1 & !d0) | (d2 & d1 & !d0) |
                  (!d3 & !d2 & !d0); // término que faltaba

    assign seg_7[4] = (!d2 & !d0) | 
                        (d3 & d2) |     
                        (d3 & d1) | 
                        (d1 & !d0); // E

    assign seg_7[5] = (!d1 & !d0) | 
                        (d3 & !d2) | 
                        (d3 & d1) | 
                        (d2 & !d0) | 
                        (!d3 & d2 & !d1); // F

    assign seg_7[6] = (d3 & !d2) | 
                        (d1 & !d0) | 
                        (d3 & d0) | 
                        (!d3 & d2 & !d1) | 
                        (!d3 & !d2 & d1); // G

    
endmodule

src/design_receptor/corrector_error.v
module corrector_error (
    input wire [6:0] recibido,  //código de Hamming recibido del transmisor del otro grupo
    input wire [2:0] sindrome, //Nos permite detectar la posición del error en el código
    output wire [3:0] dato_corregido ); // Código corregido


    //definimos s2, s1, y s0 desde el bus
    wire s2 = sindrome[2];
    wire s1 = sindrome[1];
    wire s0 = sindrome[0];


    //Lógica del decoder de 3 a 8 (por 2^3)
    wire y1 = !s2 & !s1 & s0;    //Posición 1
    wire y2 = !s2 & s1 & !s0;    // Posición 2
    wire y3 = !s2 & s1 & s0;    // Posición 3 (D0)
    wire y4 = s2 & !s1 & !s0;   // Posición 4
    wire y5 = s2 & !s1 & s0;   // Posición 5 (D1)
    wire y6 = s2 & s1 & !s0;    // Posición 6 (D2)
    wire y7 = s2 & s1 & s0;     // Posición 7 (D3)


    //Ahora hacemos los XORs para para eliminar el error en el código
    wire [6:0] limpio;
    assign limpio[0] = recibido[0] ^ y1;
    assign limpio[1] = recibido[1] ^ y2;
    assign limpio[2] = recibido[2] ^ y3;
    assign limpio[3] = recibido[3] ^ y4;
    assign limpio[4] = recibido[4] ^ y5;
    assign limpio[5] = recibido[5] ^ y6;
    assign limpio[6] = recibido[6] ^ y7;

    //Por último extraemos datos finales
    assign dato_corregido = {limpio[6], limpio[5], limpio[4], limpio[2]};


endmodule







    
endmodule

src/design/decoder_paridad.sv
module decoder_paridad (
    input wire [6:0] recibido,     // R7 a R1
    output wire [2:0] pos_error    // s2, s1, s0
);

    // -----------------------------
    // Mapeo del mensaje recibido
    // -----------------------------
    wire r1, r2, r3, r4, r5, r6, r7;

    assign r1 = recibido[0];
    assign r2 = recibido[1];
    assign r3 = recibido[2];
    assign r4 = recibido[3];
    assign r5 = recibido[4];
    assign r6 = recibido[5];
    assign r7 = recibido[6];

    // -----------------------------
    // Cálculo del síndrome
    // -----------------------------
    wire s0, s1, s2;

    assign s0 = r1 ^ r3 ^ r5 ^ r7;
    assign s1 = r2 ^ r3 ^ r6 ^ r7;
    assign s2 = r4 ^ r5 ^ r6 ^ r7;

    // -----------------------------
    // Salida
    // -----------------------------
    assign pos_error = {s2, s1, s0};

endmodule

Proyecto1/src/design/top_recep.sv
module top_recep (
    input wire [6:0] data_in,      // Código de Hamming recibido
    output wire [3:0] data_out,    // Datos corregidos
    output wire [6:0] seg_7,       // Display 7 segmentos
    output wire [3:0] leds_out     // LEDs
);

    // -----------------------------
    // Señal interna del síndrome
    // -----------------------------
    wire [2:0] pos_error;

    // -----------------------------
    // Decoder de paridad (NUEVO)
    // -----------------------------
    decoder_paridad dec_paridad (
        .recibido(data_in),
        .pos_error(pos_error)
    );

    // -----------------------------
    // Corrector de error
    // AHORA usa el síndrome real
    // -----------------------------
    corrector_error corrector (
        .recibido(data_in),
        .sindrome(pos_error),
        .dato_corregido(data_out)
    );

    // -----------------------------
    // Display 7 segmentos
    // -----------------------------
    recep_7_seg decodificador (
        .datos(data_out),
        .seg_7(seg_7)
    );

    // -----------------------------
    // LEDs
    // -----------------------------
    LEDS_display leds (
        .data_corregida(data_out),
        .leds(leds_out)
    );

endmodule

src/design_transmisor/hamm_encoder.sv

//Como input se recibe el mensaje de 4 bits y como output genera un código de hamming con 4 bits de información y 3 de paridad
module hamm_encoder (
    input wire [3:0] data_in, output[6:0] data_out);  // porque se trabaja con Hamming (7,4)

    wire d0, d1, d2, d3;  //cables internos para los bits de información

    wire p1, p2, p3;  //cables internos para bits de paridad


    assign p1 = data_in[0] ^ data_in[1] ^ data_in[3] ; //chequea datos en posiciones 3, 5 y 7
    assign p2 = data_in[0] ^ data_in[2] ^ data_in[3] ; //chequea datos en posiciones 3, 6 y 7
    assign p3 = data_in[1] ^ data_in[2] ^ data_in[3]; //chequea datos en posiciones 5, 6 y 7


    //Asignamos el output del código de Hamming. Este va en el orden:
    // d3 | d2 | d1 | p3 | d0 | p2 | p1 |
    assign data_out = {data_in[3], data_in[2], data_in[1], p3, data_in[0], p2, p1};

endmodule

src/sim/top_recep_tb.sv
`timescale 1ns/1ps

module top_recep_tb;

    reg [3:0] data_bin;        // dato original
    reg [6:0] data_in;         // código con o sin error

    wire [6:0] code_ok;        // código correcto del encoder

    wire [3:0] data_out;       // dato corregido final
    wire [6:0] seg_7;
    wire [3:0] leds_out;

    // señales internas del corrector (DEBUG)
    wire [2:0] syndrome;
    wire [2:0] error_pos;
    wire [3:0] dato_corregido;

    // =========================
    // ENCODER
    // =========================
    hamm_encoder encoder (
        .data_in(data_bin),
        .data_out(code_ok)
    );

    // =========================
    // RECEPTOR (TU SISTEMA COMPLETO)
    // =========================
    top_recep uut (
        .data_in(data_in),
        .data_out(data_out),
        .seg_7(seg_7),
        .leds_out(leds_out)
    );

    initial begin

        $dumpfile("top_recep_tb.vcd");
        $dumpvars(0, top_recep_tb);

        $display("========================================");
        $display("TESTBENCH HAMMING CON CORRECTOR");
        $display("========================================");

        // ==================================================
        // CASO 1: SIN ERROR
        // ==================================================
        data_bin = 4'b1010;
        #10;
        data_in = code_ok;
        #10;

        $display("\nCASO 1 - SIN ERROR");
        $display("data_in        = %b", data_in);
        $display("data_out       = %b", data_out);

        // ==================================================
        // CASO 2: ERROR en p1 (bit 0 de TU diseño)
        // ==================================================
        data_bin = 4'b1000;
        #10;
        data_in = code_ok;
        data_in[0] = ~data_in[0];
        #10;

        $display("\nCASO 2 - ERROR en p1");
        $display("data_in        = %b", data_in);
        $display("data_out       = %b", data_out);

        // ==================================================
        // CASO 3: ERROR en p2
        // ==================================================
        data_bin = 4'b0111;
        #10;
        data_in = code_ok;
        data_in[1] = ~data_in[1];
        #10;

        $display("\nCASO 3 - ERROR en p2");
        $display("data_in        = %b", data_in);
        $display("data_out       = %b", data_out);

        // ==================================================
        // CASO 4: ERROR en d0
        // ==================================================
        data_bin = 4'b0011;
        #10;
        data_in = code_ok;
        data_in[2] = ~data_in[2];
        #10;

        $display("\nCASO 4 - ERROR en d0");
        $display("data_in        = %b", data_in);
        $display("data_out       = %b", data_out);

        // ==================================================
        // CASO 5: ERROR en p3
        // ==================================================
        data_bin = 4'b1101;
        #10;
        data_in = code_ok;
        data_in[3] = ~data_in[3];
        #10;

        $display("\nCASO 5 - ERROR en p3");
        $display("data_in        = %b", data_in);
        $display("data_out       = %b", data_out);

        // ==================================================
        // CASO 6: ERROR en d3
        // ==================================================
        data_bin = 4'b0101;
        #10;
        data_in = code_ok;
        data_in[6] = ~data_in[6];
        #10;

        $display("\nCASO 6 - ERROR en d3");
        $display("data_in        = %b", data_in);
        $display("data_out       = %b", data_out);

        $display("\n========================================");
        $display("FIN DE SIMULACION");
        $display("========================================");

        $stop;
    end

endmodule

src/build/top_recep_tb.vcd
$date
	Thu Apr 16 02:07:24 2026
$end
$version
	Icarus Verilog
$end
$timescale
	1ps
$end
$scope module top_recep_tb $end
$var wire 7 ! seg_7 [6:0] $end
$var wire 4 " leds_out [3:0] $end
$var wire 4 # data_out [3:0] $end
$var wire 7 $ code_ok [6:0] $end
$var reg 4 % data_bin [3:0] $end
$var reg 7 & data_in [6:0] $end
$scope module encoder $end
$var wire 4 ' data_in [3:0] $end
$var wire 1 ( p1 $end
$var wire 1 ) p2 $end
$var wire 1 * p3 $end
$var wire 7 + data_out [6:0] $end
$upscope $end
$scope module uut $end
$var wire 7 , data_in [6:0] $end
$var wire 7 - seg_7 [6:0] $end
$var wire 3 . pos_error [2:0] $end
$var wire 4 / leds_out [3:0] $end
$var wire 4 0 data_out [3:0] $end
$scope module corrector $end
$var wire 7 1 recibido [6:0] $end
$var wire 1 2 y1 $end
$var wire 1 3 y2 $end
$var wire 1 4 y3 $end
$var wire 1 5 y4 $end
$var wire 1 6 y5 $end
$var wire 1 7 y6 $end
$var wire 1 8 y7 $end
$var wire 3 9 sindrome [2:0] $end
$var wire 1 : s2 $end
$var wire 1 ; s1 $end
$var wire 1 < s0 $end
$var wire 7 = limpio [6:0] $end
$var wire 4 > dato_corregido [3:0] $end
$upscope $end
$scope module dec_paridad $end
$var wire 7 ? recibido [6:0] $end
$var wire 1 @ s0 $end
$var wire 1 A s1 $end
$var wire 1 B s2 $end
$var wire 1 C r7 $end
$var wire 1 D r6 $end
$var wire 1 E r5 $end
$var wire 1 F r4 $end
$var wire 1 G r3 $end
$var wire 1 H r2 $end
$var wire 1 I r1 $end
$var wire 3 J pos_error [2:0] $end
$upscope $end
$scope module decodificador $end
$var wire 4 K datos [3:0] $end
$var wire 7 L seg_7 [6:0] $end
$var wire 1 M d3 $end
$var wire 1 N d2 $end
$var wire 1 O d1 $end
$var wire 1 P d0 $end
$upscope $end
$scope module leds $end
$var wire 4 Q data_corregida [3:0] $end
$var wire 4 R leds [3:0] $end
$upscope $end
$upscope $end
$upscope $end
$enddefinitions $end
$comment Show the parameter values. $end
$dumpall
$end
#0
$dumpvars
bx R
bx Q
xP
xO
xN
xM
bx L
bx K
bx J
xI
xH
xG
xF
xE
xD
xC
xB
xA
x@
bx ?
bx >
bx =
x<
x;
x:
bx 9
x8
x7
x6
x5
x4
x3
x2
bx 1
bx 0
bx /
bx .
bx -
bx ,
b1010010 +
0*
1)
0(
b1010 '
bx &
b1010 %
b1010010 $
bx #
bx "
bx !
$end
#10000
b1110111 !
b1110111 -
b1110111 L
0N
1M
1O
0P
b1010 "
b1010 /
b1010 R
b1010 #
b1010 0
b1010 >
b1010 K
b1010 Q
05
07
03
b1010010 =
08
06
04
02
0:
0;
0<
0B
0A
b0 .
b0 9
b0 J
0@
1C
0D
1E
0F
0G
1H
0I
b1010010 &
b1010010 ,
b1010010 1
b1010010 ?
#20000
1(
1*
b1001011 $
b1001011 +
b1000 %
b1000 '
#30000
b1111111 !
b1111111 -
b1111111 L
12
0O
1<
b1000 "
b1000 /
b1000 R
b1000 #
b1000 0
b1000 >
b1000 K
b1000 Q
b1 .
b1 9
b1 J
1@
b1001011 =
0E
1F
b1001010 &
b1001010 ,
b1001010 1
b1001010 ?
#40000
0(
0)
0*
b110100 $
b110100 +
b111 %
b111 '
#50000
b111 !
b111 -
b111 L
13
1P
1O
1N
0M
02
b111 "
b111 /
b111 R
b111 #
b111 0
b111 >
b111 K
b111 Q
1;
0<
b110100 =
1A
b10 .
b10 9
b10 J
0@
0C
1D
1E
0F
1G
b110110 &
b110110 ,
b110110 1
b110110 ?
#60000
1)
1*
b11110 $
b11110 +
b11 %
b11 '
#70000
14
b1001111 !
b1001111 -
b1001111 L
02
03
1<
1P
1@
0N
1;
b11 "
b11 /
b11 R
b11 #
b11 0
b11 >
b11 K
b11 Q
b11 .
b11 9
b11 J
1A
b11110 =
0G
0D
1F
b11010 &
b11010 ,
b11010 1
b11010 ?
#80000
0(
1)
0*
b1100110 $
b1100110 +
b1101 %
b1101 '
#90000
b1011110 !
b1011110 -
b1011110 L
15
1P
0O
1N
1M
03
04
b1101 "
b1101 /
b1101 R
b1101 #
b1101 0
b1101 >
b1101 K
b1101 Q
1:
0;
0<
b1100110 =
1B
0A
b100 .
b100 9
b100 J
0@
1C
1D
0E
1G
b1101110 &
b1101110 ,
b1101110 1
b1101110 ?
#100000
1(
1*
b1111111 $
b1111111 +
b1111 %
b1111 '
#110000
1P
b1110101 !
b1110101 -
b1110101 L
18
04
1M
05
06
1O
1:
1;
1<
b1111 "
b1111 /
b1111 R
b1111 #
b1111 0
b1111 >
b1111 K
b1111 Q
1B
1A
b111 .
b111 9
b111 J
1@
b1111111 =
0C
1E
1I
b111111 &
b111111 ,
b111111 1
b111111 ?
